{"nodes": [{"id": "c_xampp_htdocs_projects_twenty_routes_api_php", "label": "api.php", "file_type": "code", "source_file": "routes/api.php", "source_location": "L1"}], "edges": [{"source": "c_xampp_htdocs_projects_twenty_routes_api_php", "target": "route", "relation": "imports", "context": "import", "confidence": "EXTRACTED", "source_file": "routes/api.php", "source_location": "L3", "weight": 1.0}, {"source": "c_xampp_htdocs_projects_twenty_routes_api_php", "target": "aboutuscontroller", "relation": "imports", "context": "import", "confidence": "EXTRACTED", "source_file": "routes/api.php", "source_location": "L6", "weight": 1.0}, {"source": "c_xampp_htdocs_projects_twenty_routes_api_php", "target": "indicatorcontroller", "relation": "imports", "context": "import", "confidence": "EXTRACTED", "source_file": "routes/api.php", "source_location": "L7", "weight": 1.0}, {"source": "c_xampp_htdocs_projects_twenty_routes_api_php", "target": "messagecontroller", "relation": "imports", "context": "import", "confidence": "EXTRACTED", "source_file": "routes/api.php", "source_location": "L8", "weight": 1.0}, {"source": "c_xampp_htdocs_projects_twenty_routes_api_php", "target": "complaintcontroller", "relation": "imports", "context": "import", "confidence": "EXTRACTED", "source_file": "routes/api.php", "source_location": "L9", "weight": 1.0}, {"source": "c_xampp_htdocs_projects_twenty_routes_api_php", "target": "whistleblowingcontroller", "relation": "imports", "context": "import", "confidence": "EXTRACTED", "source_file": "routes/api.php", "source_location": "L10", "weight": 1.0}, {"source": "c_xampp_htdocs_projects_twenty_routes_api_php", "target": "slidercontroller", "relation": "imports", "context": "import", "confidence": "EXTRACTED", "source_file": "routes/api.php", "source_location": "L11", "weight": 1.0}, {"source": "c_xampp_htdocs_projects_twenty_routes_api_php", "target": "testimonycontroller", "relation": "imports", "context": "import", "confidence": "EXTRACTED", "source_file": "routes/api.php", "source_location": "L12", "weight": 1.0}, {"source": "c_xampp_htdocs_projects_twenty_routes_api_php", "target": "casestudycontroller", "relation": "imports", "context": "import", "confidence": "EXTRACTED", "source_file": "routes/api.php", "source_location": "L13", "weight": 1.0}, {"source": "c_xampp_htdocs_projects_twenty_routes_api_php", "target": "subscriptioncontroller", "relation": "imports", "context": "import", "confidence": "EXTRACTED", "source_file": "routes/api.php", "source_location": "L14", "weight": 1.0}, {"source": "c_xampp_htdocs_projects_twenty_routes_api_php", "target": "categorycontroller", "relation": "imports", "context": "import", "confidence": "EXTRACTED", "source_file": "routes/api.php", "source_location": "L15", "weight": 1.0}, {"source": "c_xampp_htdocs_projects_twenty_routes_api_php", "target": "blogcategorycontroller", "relation": "imports", "context": "import", "confidence": "EXTRACTED", "source_file": "routes/api.php", "source_location": "L16", "weight": 1.0}, {"source": "c_xampp_htdocs_projects_twenty_routes_api_php", "target": "collectioncontroller", "relation": "imports", "context": "import", "confidence": "EXTRACTED", "source_file": "routes/api.php", "source_location": "L18", "weight": 1.0}, {"source": "c_xampp_htdocs_projects_twenty_routes_api_php", "target": "postcontroller", "relation": "imports", "context": "import", "confidence": "EXTRACTED", "source_file": "routes/api.php", "source_location": "L19", "weight": 1.0}, {"source": "c_xampp_htdocs_projects_twenty_routes_api_php", "target": "innovationcontroller", "relation": "imports", "context": "import", "confidence": "EXTRACTED", "source_file": "routes/api.php", "source_location": "L20", "weight": 1.0}, {"source": "c_xampp_htdocs_projects_twenty_routes_api_php", "target": "applicationcontroller", "relation": "imports", "context": "import", "confidence": "EXTRACTED", "source_file": "routes/api.php", "source_location": "L21", "weight": 1.0}, {"source": "c_xampp_htdocs_projects_twenty_routes_api_php", "target": "attributecontroller", "relation": "imports", "context": "import", "confidence": "EXTRACTED", "source_file": "routes/api.php", "source_location": "L22", "weight": 1.0}, {"source": "c_xampp_htdocs_projects_twenty_routes_api_php", "target": "servicecontroller", "relation": "imports", "context": "import", "confidence": "EXTRACTED", "source_file": "routes/api.php", "source_location": "L23", "weight": 1.0}, {"source": "c_xampp_htdocs_projects_twenty_routes_api_php", "target": "servicecategorycontroller", "relation": "imports", "context": "import", "confidence": "EXTRACTED", "source_file": "routes/api.php", "source_location": "L24", "weight": 1.0}, {"source": "c_xampp_htdocs_projects_twenty_routes_api_php", "target": "servicesubcategorycontroller", "relation": "imports", "context": "import", "confidence": "EXTRACTED", "source_file": "routes/api.php", "source_location": "L25", "weight": 1.0}, {"source": "c_xampp_htdocs_projects_twenty_routes_api_php", "target": "socialcontroller", "relation": "imports", "context": "import", "confidence": "EXTRACTED", "source_file": "routes/api.php", "source_location": "L26", "weight": 1.0}, {"source": "c_xampp_htdocs_projects_twenty_routes_api_php", "target": "strengthcontroller", "relation": "imports", "context": "import", "confidence": "EXTRACTED", "source_file": "routes/api.php", "source_location": "L27", "weight": 1.0}, {"source": "c_xampp_htdocs_projects_twenty_routes_api_php", "target": "benefitcontroller", "relation": "imports", "context": "import", "confidence": "EXTRACTED", "source_file": "routes/api.php", "source_location": "L28", "weight": 1.0}, {"source": "c_xampp_htdocs_projects_twenty_routes_api_php", "target": "appcontroller", "relation": "imports", "context": "import", "confidence": "EXTRACTED", "source_file": "routes/api.php", "source_location": "L29", "weight": 1.0}, {"source": "c_xampp_htdocs_projects_twenty_routes_api_php", "target": "certificationcontroller", "relation": "imports", "context": "import", "confidence": "EXTRACTED", "source_file": "routes/api.php", "source_location": "L30", "weight": 1.0}, {"source": "c_xampp_htdocs_projects_twenty_routes_api_php", "target": "providercontroller", "relation": "imports", "context": "import", "confidence": "EXTRACTED", "source_file": "routes/api.php", "source_location": "L31", "weight": 1.0}, {"source": "c_xampp_htdocs_projects_twenty_routes_api_php", "target": "partnercontroller", "relation": "imports", "context": "import", "confidence": "EXTRACTED", "source_file": "routes/api.php", "source_location": "L32", "weight": 1.0}, {"source": "c_xampp_htdocs_projects_twenty_routes_api_php", "target": "generalcontroller", "relation": "imports", "context": "import", "confidence": "EXTRACTED", "source_file": "routes/api.php", "source_location": "L33", "weight": 1.0}, {"source": "c_xampp_htdocs_projects_twenty_routes_api_php", "target": "profilecontroller", "relation": "imports", "context": "import", "confidence": "EXTRACTED", "source_file": "routes/api.php", "source_location": "L34", "weight": 1.0}, {"source": "c_xampp_htdocs_projects_twenty_routes_api_php", "target": "accountcontroller", "relation": "imports", "context": "import", "confidence": "EXTRACTED", "source_file": "routes/api.php", "source_location": "L35", "weight": 1.0}, {"source": "c_xampp_htdocs_projects_twenty_routes_api_php", "target": "adcontroller", "relation": "imports", "context": "import", "confidence": "EXTRACTED", "source_file": "routes/api.php", "source_location": "L36", "weight": 1.0}, {"source": "c_xampp_htdocs_projects_twenty_routes_api_php", "target": "bannercontroller", "relation": "imports", "context": "import", "confidence": "EXTRACTED", "source_file": "routes/api.php", "source_location": "L37", "weight": 1.0}, {"source": "c_xampp_htdocs_projects_twenty_routes_api_php", "target": "brandcontroller", "relation": "imports", "context": "import", "confidence": "EXTRACTED", "source_file": "routes/api.php", "source_location": "L38", "weight": 1.0}, {"source": "c_xampp_htdocs_projects_twenty_routes_api_php", "target": "discountrulescontroller", "relation": "imports", "context": "import", "confidence": "EXTRACTED", "source_file": "routes/api.php", "source_location": "L39", "weight": 1.0}, {"source": "c_xampp_htdocs_projects_twenty_routes_api_php", "target": "amenitycontroller", "relation": "imports", "context": "import", "confidence": "EXTRACTED", "source_file": "routes/api.php", "source_location": "L40", "weight": 1.0}, {"source": "c_xampp_htdocs_projects_twenty_routes_api_php", "target": "bookingcontroller", "relation": "imports", "context": "import", "confidence": "EXTRACTED", "source_file": "routes/api.php", "source_location": "L41", "weight": 1.0}, {"source": "c_xampp_htdocs_projects_twenty_routes_api_php", "target": "roomavailabilitycontroller", "relation": "imports", "context": "import", "confidence": "EXTRACTED", "source_file": "routes/api.php", "source_location": "L42", "weight": 1.0}, {"source": "c_xampp_htdocs_projects_twenty_routes_api_php", "target": "packagingcontroller", "relation": "imports", "context": "import", "confidence": "EXTRACTED", "source_file": "routes/api.php", "source_location": "L43", "weight": 1.0}, {"source": "c_xampp_htdocs_projects_twenty_routes_api_php", "target": "deliverypricecontroller", "relation": "imports", "context": "import", "confidence": "EXTRACTED", "source_file": "routes/api.php", "source_location": "L45", "weight": 1.0}, {"source": "c_xampp_htdocs_projects_twenty_routes_api_php", "target": "typesdeliverycontroller", "relation": "imports", "context": "import", "confidence": "EXTRACTED", "source_file": "routes/api.php", "source_location": "L46", "weight": 1.0}, {"source": "c_xampp_htdocs_projects_twenty_routes_api_php", "target": "storecontroller", "relation": "imports", "context": "import", "confidence": "EXTRACTED", "source_file": "routes/api.php", "source_location": "L47", "weight": 1.0}, {"source": "c_xampp_htdocs_projects_twenty_routes_api_php", "target": "gallerycontroller", "relation": "imports", "context": "import", "confidence": "EXTRACTED", "source_file": "routes/api.php", "source_location": "L48", "weight": 1.0}, {"source": "c_xampp_htdocs_projects_twenty_routes_api_php", "target": "itemcontroller", "relation": "imports", "context": "import", "confidence": "EXTRACTED", "source_file": "routes/api.php", "source_location": "L49", "weight": 1.0}, {"source": "c_xampp_htdocs_projects_twenty_routes_api_php", "target": "salecontroller", "relation": "imports", "context": "import", "confidence": "EXTRACTED", "source_file": "routes/api.php", "source_location": "L50", "weight": 1.0}, {"source": "c_xampp_htdocs_projects_twenty_routes_api_php", "target": "saleexportcontroller", "relation": "imports", "context": "import", "confidence": "EXTRACTED", "source_file": "routes/api.php", "source_location": "L51", "weight": 1.0}, {"source": "c_xampp_htdocs_projects_twenty_routes_api_php", "target": "homecontroller", "relation": "imports", "context": "import", "confidence": "EXTRACTED", "source_file": "routes/api.php", "source_location": "L52", "weight": 1.0}, {"source": "c_xampp_htdocs_projects_twenty_routes_api_php", "target": "salecontroller", "relation": "imports", "context": "import", "confidence": "EXTRACTED", "source_file": "routes/api.php", "source_location": "L53", "weight": 1.0}, {"source": "c_xampp_htdocs_projects_twenty_routes_api_php", "target": "subcategorycontroller", "relation": "imports", "context": "import", "confidence": "EXTRACTED", "source_file": "routes/api.php", "source_location": "L55", "weight": 1.0}, {"source": "c_xampp_htdocs_projects_twenty_routes_api_php", "target": "systemcolorcontroller", "relation": "imports", "context": "import", "confidence": "EXTRACTED", "source_file": "routes/api.php", "source_location": "L56", "weight": 1.0}, {"source": "c_xampp_htdocs_projects_twenty_routes_api_php", "target": "systemcontroller", "relation": "imports", "context": "import", "confidence": "EXTRACTED", "source_file": "routes/api.php", "source_location": "L57", "weight": 1.0}, {"source": "c_xampp_htdocs_projects_twenty_routes_api_php", "target": "tagcontroller", "relation": "imports", "context": "import", "confidence": "EXTRACTED", "source_file": "routes/api.php", "source_location": "L58", "weight": 1.0}, {"source": "c_xampp_htdocs_projects_twenty_routes_api_php", "target": "posttagcontroller", "relation": "imports", "context": "import", "confidence": "EXTRACTED", "source_file": "routes/api.php", "source_location": "L59", "weight": 1.0}, {"source": "c_xampp_htdocs_projects_twenty_routes_api_php", "target": "webdetailcontroller", "relation": "imports", "context": "import", "confidence": "EXTRACTED", "source_file": "routes/api.php", "source_location": "L60", "weight": 1.0}, {"source": "c_xampp_htdocs_projects_twenty_routes_api_php", "target": "itemimagecontroller", "relation": "imports", "context": "import", "confidence": "EXTRACTED", "source_file": "routes/api.php", "source_location": "L62", "weight": 1.0}, {"source": "c_xampp_htdocs_projects_twenty_routes_api_php", "target": "faqcontroller", "relation": "imports", "context": "import", "confidence": "EXTRACTED", "source_file": "routes/api.php", "source_location": "L63", "weight": 1.0}, {"source": "c_xampp_htdocs_projects_twenty_routes_api_php", "target": "rankcontroller", "relation": "imports", "context": "import", "confidence": "EXTRACTED", "source_file": "routes/api.php", "source_location": "L64", "weight": 1.0}, {"source": "c_xampp_htdocs_projects_twenty_routes_api_php", "target": "rankbonuscontroller", "relation": "imports", "context": "import", "confidence": "EXTRACTED", "source_file": "routes/api.php", "source_location": "L65", "weight": 1.0}, {"source": "c_xampp_htdocs_projects_twenty_routes_api_php", "target": "combocontroller", "relation": "imports", "context": "import", "confidence": "EXTRACTED", "source_file": "routes/api.php", "source_location": "L66", "weight": 1.0}, {"source": "c_xampp_htdocs_projects_twenty_routes_api_php", "target": "relatedgroupcontroller", "relation": "imports", "context": "import", "confidence": "EXTRACTED", "source_file": "routes/api.php", "source_location": "L67", "weight": 1.0}, {"source": "c_xampp_htdocs_projects_twenty_routes_api_php", "target": "deliveryzonecontroller", "relation": "imports", "context": "import", "confidence": "EXTRACTED", "source_file": "routes/api.php", "source_location": "L68", "weight": 1.0}, {"source": "c_xampp_htdocs_projects_twenty_routes_api_php", "target": "imageuploadcontroller", "relation": "imports", "context": "import", "confidence": "EXTRACTED", "source_file": "routes/api.php", "source_location": "L69", "weight": 1.0}, {"source": "c_xampp_htdocs_projects_twenty_routes_api_php", "target": "notificationvariablecontroller", "relation": "imports", "context": "import", "confidence": "EXTRACTED", "source_file": "routes/api.php", "source_location": "L70", "weight": 1.0}, {"source": "c_xampp_htdocs_projects_twenty_routes_api_php", "target": "notificationvariablescontroller", "relation": "imports", "context": "import", "confidence": "EXTRACTED", "source_file": "routes/api.php", "source_location": "L71", "weight": 1.0}, {"source": "c_xampp_htdocs_projects_twenty_routes_api_php", "target": "repositorycontroller", "relation": "imports", "context": "import", "confidence": "EXTRACTED", "source_file": "routes/api.php", "source_location": "L72", "weight": 1.0}, {"source": "c_xampp_htdocs_projects_twenty_routes_api_php", "target": "settingcontroller", "relation": "imports", "context": "import", "confidence": "EXTRACTED", "source_file": "routes/api.php", "source_location": "L73", "weight": 1.0}, {"source": "c_xampp_htdocs_projects_twenty_routes_api_php", "target": "couponcontroller", "relation": "imports", "context": "import", "confidence": "EXTRACTED", "source_file": "routes/api.php", "source_location": "L74", "weight": 1.0}, {"source": "c_xampp_htdocs_projects_twenty_routes_api_php", "target": "salestatuscontroller", "relation": "imports", "context": "import", "confidence": "EXTRACTED", "source_file": "routes/api.php", "source_location": "L75", "weight": 1.0}, {"source": "c_xampp_htdocs_projects_twenty_routes_api_php", "target": "usercontroller", "relation": "imports", "context": "import", "confidence": "EXTRACTED", "source_file": "routes/api.php", "source_location": "L76", "weight": 1.0}, {"source": "c_xampp_htdocs_projects_twenty_routes_api_php", "target": "clientcontroller", "relation": "imports", "context": "import", "confidence": "EXTRACTED", "source_file": "routes/api.php", "source_location": "L77", "weight": 1.0}, {"source": "c_xampp_htdocs_projects_twenty_routes_api_php", "target": "sellercontroller", "relation": "imports", "context": "import", "confidence": "EXTRACTED", "source_file": "routes/api.php", "source_location": "L78", "weight": 1.0}, {"source": "c_xampp_htdocs_projects_twenty_routes_api_php", "target": "jobapplicationcontroller", "relation": "imports", "context": "import", "confidence": "EXTRACTED", "source_file": "routes/api.php", "source_location": "L79", "weight": 1.0}, {"source": "c_xampp_htdocs_projects_twenty_routes_api_php", "target": "fillablecontroller", "relation": "imports", "context": "import", "confidence": "EXTRACTED", "source_file": "routes/api.php", "source_location": "L80", "weight": 1.0}, {"source": "c_xampp_htdocs_projects_twenty_routes_api_php", "target": "rolehasmenucontroller", "relation": "imports", "context": "import", "confidence": "EXTRACTED", "source_file": "routes/api.php", "source_location": "L81", "weight": 1.0}, {"source": "c_xampp_htdocs_projects_twenty_routes_api_php", "target": "authclientcontroller", "relation": "imports", "context": "import", "confidence": "EXTRACTED", "source_file": "routes/api.php", "source_location": "L82", "weight": 1.0}, {"source": "c_xampp_htdocs_projects_twenty_routes_api_php", "target": "jobapplicationcontroller", "relation": "imports", "context": "import", "confidence": "EXTRACTED", "source_file": "routes/api.php", "source_location": "L83", "weight": 1.0}, {"source": "c_xampp_htdocs_projects_twenty_routes_api_php", "target": "authcontroller", "relation": "imports", "context": "import", "confidence": "EXTRACTED", "source_file": "routes/api.php", "source_location": "L85", "weight": 1.0}, {"source": "c_xampp_htdocs_projects_twenty_routes_api_php", "target": "blogcategorycontroller", "relation": "imports", "context": "import", "confidence": "EXTRACTED", "source_file": "routes/api.php", "source_location": "L86", "weight": 1.0}, {"source": "c_xampp_htdocs_projects_twenty_routes_api_php", "target": "blogcontroller", "relation": "imports", "context": "import", "confidence": "EXTRACTED", "source_file": "routes/api.php", "source_location": "L87", "weight": 1.0}, {"source": "c_xampp_htdocs_projects_twenty_routes_api_php", "target": "complaintcontroller", "relation": "imports", "context": "import", "confidence": "EXTRACTED", "source_file": "routes/api.php", "source_location": "L88", "weight": 1.0}, {"source": "c_xampp_htdocs_projects_twenty_routes_api_php", "target": "whistleblowingcontroller", "relation": "imports", "context": "import", "confidence": "EXTRACTED", "source_file": "routes/api.php", "source_location": "L89", "weight": 1.0}, {"source": "c_xampp_htdocs_projects_twenty_routes_api_php", "target": "covercontroller", "relation": "imports", "context": "import", "confidence": "EXTRACTED", "source_file": "routes/api.php", "source_location": "L90", "weight": 1.0}, {"source": "c_xampp_htdocs_projects_twenty_routes_api_php", "target": "couponcontroller", "relation": "imports", "context": "import", "confidence": "EXTRACTED", "source_file": "routes/api.php", "source_location": "L91", "weight": 1.0}, {"source": "c_xampp_htdocs_projects_twenty_routes_api_php", "target": "deliverypricecontroller", "relation": "imports", "context": "import", "confidence": "EXTRACTED", "source_file": "routes/api.php", "source_location": "L92", "weight": 1.0}, {"source": "c_xampp_htdocs_projects_twenty_routes_api_php", "target": "typedeliverycontroller", "relation": "imports", "context": "import", "confidence": "EXTRACTED", "source_file": "routes/api.php", "source_location": "L93", "weight": 1.0}, {"source": "c_xampp_htdocs_projects_twenty_routes_api_php", "target": "itemcontroller", "relation": "imports", "context": "import", "confidence": "EXTRACTED", "source_file": "routes/api.php", "source_location": "L94", "weight": 1.0}, {"source": "c_xampp_htdocs_projects_twenty_routes_api_php", "target": "itemimportcontroller", "relation": "imports", "context": "import", "confidence": "EXTRACTED", "source_file": "routes/api.php", "source_location": "L95", "weight": 1.0}, {"source": "c_xampp_htdocs_projects_twenty_routes_api_php", "target": "messagecontroller", "relation": "imports", "context": "import", "confidence": "EXTRACTED", "source_file": "routes/api.php", "source_location": "L96", "weight": 1.0}, {"source": "c_xampp_htdocs_projects_twenty_routes_api_php", "target": "paymentcontroller", "relation": "imports", "context": "import", "confidence": "EXTRACTED", "source_file": "routes/api.php", "source_location": "L97", "weight": 1.0}, {"source": "c_xampp_htdocs_projects_twenty_routes_api_php", "target": "bookingcontroller", "relation": "imports", "context": "import", "confidence": "EXTRACTED", "source_file": "routes/api.php", "source_location": "L98", "weight": 1.0}, {"source": "c_xampp_htdocs_projects_twenty_routes_api_php", "target": "roomavailabilitycontroller", "relation": "imports", "context": "import", "confidence": "EXTRACTED", "source_file": "routes/api.php", "source_location": "L99", "weight": 1.0}, {"source": "c_xampp_htdocs_projects_twenty_routes_api_php", "target": "mercadopagocontroller", "relation": "imports", "context": "import", "confidence": "EXTRACTED", "source_file": "routes/api.php", "source_location": "L100", "weight": 1.0}, {"source": "c_xampp_htdocs_projects_twenty_routes_api_php", "target": "openpaycontroller", "relation": "imports", "context": "import", "confidence": "EXTRACTED", "source_file": "routes/api.php", "source_location": "L101", "weight": 1.0}, {"source": "c_xampp_htdocs_projects_twenty_routes_api_php", "target": "personcontroller", "relation": "imports", "context": "import", "confidence": "EXTRACTED", "source_file": "routes/api.php", "source_location": "L102", "weight": 1.0}, {"source": "c_xampp_htdocs_projects_twenty_routes_api_php", "target": "postcontroller", "relation": "imports", "context": "import", "confidence": "EXTRACTED", "source_file": "routes/api.php", "source_location": "L103", "weight": 1.0}, {"source": "c_xampp_htdocs_projects_twenty_routes_api_php", "target": "salecontroller", "relation": "imports", "context": "import", "confidence": "EXTRACTED", "source_file": "routes/api.php", "source_location": "L104", "weight": 1.0}, {"source": "c_xampp_htdocs_projects_twenty_routes_api_php", "target": "subscriptioncontroller", "relation": "imports", "context": "import", "confidence": "EXTRACTED", "source_file": "routes/api.php", "source_location": "L105", "weight": 1.0}, {"source": "c_xampp_htdocs_projects_twenty_routes_api_php", "target": "scrapcontroller", "relation": "imports", "context": "import", "confidence": "EXTRACTED", "source_file": "routes/api.php", "source_location": "L106", "weight": 1.0}, {"source": "c_xampp_htdocs_projects_twenty_routes_api_php", "target": "strengthcontroller", "relation": "imports", "context": "import", "confidence": "EXTRACTED", "source_file": "routes/api.php", "source_location": "L107", "weight": 1.0}, {"source": "c_xampp_htdocs_projects_twenty_routes_api_php", "target": "benefitcontroller", "relation": "imports", "context": "import", "confidence": "EXTRACTED", "source_file": "routes/api.php", "source_location": "L108", "weight": 1.0}, {"source": "c_xampp_htdocs_projects_twenty_routes_api_php", "target": "applicationcontroller", "relation": "imports", "context": "import", "confidence": "EXTRACTED", "source_file": "routes/api.php", "source_location": "L109", "weight": 1.0}, {"source": "c_xampp_htdocs_projects_twenty_routes_api_php", "target": "socialcontroller", "relation": "imports", "context": "import", "confidence": "EXTRACTED", "source_file": "routes/api.php", "source_location": "L110", "weight": 1.0}, {"source": "c_xampp_htdocs_projects_twenty_routes_api_php", "target": "temporalyimagecontroller", "relation": "imports", "context": "import", "confidence": "EXTRACTED", "source_file": "routes/api.php", "source_location": "L111", "weight": 1.0}, {"source": "c_xampp_htdocs_projects_twenty_routes_api_php", "target": "unifiedimportcontroller", "relation": "imports", "context": "import", "confidence": "EXTRACTED", "source_file": "routes/api.php", "source_location": "L112", "weight": 1.0}, {"source": "c_xampp_htdocs_projects_twenty_routes_api_php", "target": "packagingcontroller", "relation": "imports", "context": "import", "confidence": "EXTRACTED", "source_file": "routes/api.php", "source_location": "L113", "weight": 1.0}], "raw_calls": []}